[
  {
      "id": 0,
      "question": "(Jimmy of the Clue Crew shows an animated diagram of a spider casting a web on the monitor.)  To create webs, some spiders release a silk thread in hopes that this aeolian process will help the silk attach to something solid",
      "answer": "wind",
      "played": false,
      "price": 400,
      "category": "world wide webs"
  },
  {
      "id": 1,
      "question": "Like a fisherman, the spider seen here casts a unique web called one of these over its doomed prey",
      "answer": "a net",
      "played": false,
      "price": 200,
      "category": "world wide webs"
  },
  {

      "id": 2,
      "question": "(Jimmy of the Clue Crew shows an animated diagram of a spider casting a web on the monitor.)  To create webs, some spiders release a silk thread in hopes that this aeolian process will help the silk attach to something solid",
      "answer": "wind",
      "played": false,
      "price": 400,
      "category": "world wide webs"
  },
  {
    
      "id": 3,
      "question": "Spiders don't just use their silk to make webs, they also use them to make these egg enclosures",
      "answer": "cocoons",
      "played": false,
      "price": 600,
      "category": "world wide webs"
  },
  {
      "id": 4,
      "question": "Found in Australia, the spider seen here is named for this saint, whose cross is seen on Scotland's flag",
      "answer": "St. Andrew",
      "played": false,
      "price": 800,
      "category": "world wide webs"
  },
  {
      "id": 5,
      "question": "(Kelly of the Clue Crew shows an animated diagram of a spider completing a web on the monitor.)  The catching spiral is covered with a sticky substance & stops short of the center of the web, known as this 3-letter word, just like the middle of a wheel",
      "answer": "hub",
      "played": false,
      "price": 1000,
      "category": "world wide webs"
  },
  {
      "id": 6,
      "question": "If the show's named after you, they can't kill you off over a contract spat, can they?  Hmm... ask this \"Valerie\" star",
      "answer": "Valerie Harper",
      "played": false,
      "price": 200,
      "category": "contract killings"
  },
  {
      "id": 7,
      "question": "If the show's named after you, they can't kill you off over a contract spat, can they?  Hmm... ask this \"Valerie\" star",
      "answer": "Valerie Harper",
      "played": false,
      "price": 200,
      "category": "contract killings"
  },
  {
      "id": 8,
      "question": "He co-starred as Detective Falconer on \"Sisters\" until he was needed for \"ER\"--uh oh, car bomb!",
      "answer": "George Clooney",
      "played": false,
      "price": 400,
      "category": "contract killings"
  },
  {
      "id": 9,
      "question": "The actress voicing Maude, wife of this \"Simpsons\" guy, asked for weekly flights from L.A. to home--Bye-diddily-eye!",
      "answer": "Ned Flanders",
      "played": false,
      "price": 600,
      "category": "contract killings"
  },
  {
      "id": 10,
      "question": "Jay Thomas talked smack about Rhea Perlman, his TV wife on this show; look out for that Zamboni, Eddie!",
      "answer": "<i>Cheers</i>",
      "played": false,
      "price": 800,
      "category": "contract killings"
  },
  {
      "id": 11,
      "question": "When Susan St. James asked for a raise on this Rock Hudson show, the \"and Wife\" met with an accident",
      "answer": "<i>McMillan & Wife</i>",
      "played": false,
      "price": 1000,
      "category": "contract killings"
  },
  {
      "id": 12,
      "question": "A hunky hurler:ROTH",
      "answer": "Thor",
      "played": false,
      "price": 200,
      "category": "scrambled gods & goddesses"
  },
  {
      "id": 13,
      "question": "A hunky hurler:ROTH",
      "answer": "Thor",
      "played": false,
      "price": 200,
      "category": "scrambled gods & goddesses"
  },
  {
      "id": 14,
      "question": "She's Mrs. Osiris:SI SI",
      "answer": "Isis",
      "played": false,
      "price": 400,
      "category": "scrambled gods & goddesses"
  },
  {
      "id": 15,
      "question": "Apollo's sister:A MISTER",
      "answer": "Artemis",
      "played": false,
      "price": 600,
      "category": "scrambled gods & goddesses"
  },
  {
      "id": 16,
      "question": "Babylonian babe:HI STAR",
      "answer": "Ishtar",
      "played": false,
      "price": 800,
      "category": "scrambled gods & goddesses"
  },
  {
      "id": 17,
      "question": "He's swift of foot:MY CURER",
      "answer": "Mercury",
      "played": false,
      "price": 1000,
      "category": "scrambled gods & goddesses"
  },
  {
      "id": 18,
      "question": "When we first meet this title character in a 2008 Pixar film, his only friend is his pet, cockroach, Hal",
      "answer": "WALL\u0095E",
      "played": false,
      "price": 200,
      "category": "pet projects"
  },
  {
      "id": 19,
      "question": "When we first meet this title character in a 2008 Pixar film, his only friend is his pet, cockroach, Hal",
      "answer": "WALL\u0095E",
      "played": false,
      "price": 200,
      "category": "pet projects"
  },
  {
      "id": 20,
      "question": "Monsieur Le Pelt joins Cruella de Vil in the chase for 102 of these in a 2000 sequel",
      "answer": "Dalmatians",
      "played": false,
      "price": 400,
      "category": "pet projects"
  },
  {
      "id": 21,
      "question": "Yes, that's Hayden Panettiere befriending one of these animals (who thinks he's a racehorse) in \"Racing Stripes\"",
      "answer": "a zebra",
      "played": false,
      "price": 600,
      "category": "pet projects"
  },
  {
      "id": 22,
      "question": "When Andi & Bruce need to find a place for their pup to live, they create this title lodging in a 2008 film",
      "answer": "a hotel for dogs",
      "played": false,
      "price": 800,
      "category": "pet projects"
  },
  {
      "id": 23,
      "question": "In a 2007 film this mutt was able to leap tall buildings in a single bound after a mishap in the lab of Simon Barsinister",
      "answer": "Underdog",
      "played": false,
      "price": 1000,
      "category": "pet projects"
  },
  {
      "id": 24,
      "question": "Dry a grape & it becomes this",
      "answer": "a raisin",
      "played": false,
      "price": 200,
      "category": "transformed food"
  },
  {
      "id": 25,
      "question": "Dry a grape & it becomes this",
      "answer": "a raisin",
      "played": false,
      "price": 200,
      "category": "transformed food"
  },
  {
      "id": 26,
      "question": "A prune is this fruit before it becomes shriveled",
      "answer": "a plum",
      "played": false,
      "price": 400,
      "category": "transformed food"
  },
  {
      "id": 27,
      "question": "A cucumber that's put in a solution called brine becomes this",
      "answer": "a pickle",
      "played": false,
      "price": 600,
      "category": "transformed food"
  },
  {
      "id": 28,
      "question": "Warm some milk & add specialized bacteria, separate out the curd clumps, then shape & age the curd to make this",
      "answer": "cheese",
      "played": false,
      "price": 800,
      "category": "transformed food"
  },
  {
      "id": 29,
      "question": "Take a legume whose pod develops underground, roast it, then grind it into a paste to make this",
      "answer": "peanut butter",
      "played": false,
      "price": 1000,
      "category": "transformed food"
  }
]